{"Entities": [{"DescriptiveMentionIndex": [0], "Mentions": [{"BeginOffset": 0, "EndOffset": 1, "Score": 0.999997, "GroupScore": 1.0, "Text": "I", "Type": "PERSON", "MentionSentiment": {"Sentiment": "NEUTRAL", "SentimentScore": {"Mixed": 0.0, "Negative": 0.0, "Neutral": 1.0, "Positive": 0.0}}}]}, {"DescriptiveMentionIndex": [0], "Mentions": [{"BeginOffset": 8, "EndOffset": 11, "Score": 0.999945, "GroupScore": 1.0, "Text": "one", "Type": "QUANTITY", "MentionSentiment": {"Sentiment": "NEUTRAL", "SentimentScore": {"Mixed": 0.0, "Negative": 0.0, "Neutral": 1.0, "Positive": 0.0}}}]}, {"DescriptiveMentionIndex": [0], "Mentions": [{"BeginOffset": 15, "EndOffset": 20, "Score": 0.949854, "GroupScore": 1.0, "Text": "their", "Type": "BRAND", "MentionSentiment": {"Sentiment": "NEUTRAL", "SentimentScore": {"Mixed": 0.0, "Negative": 0.0, "Neutral": 1.0, "Positive": 0.0}}}]}, {"DescriptiveMentionIndex": [0], "Mentions": [{"BeginOffset": 21, "EndOffset": 26, "Score": 0.999813, "GroupScore": 1.0, "Text": "spicy", "Type": "OTHER", "MentionSentiment": {"Sentiment": "NEUTRAL", "SentimentScore": {"Mixed": 0.000237, "Negative": 3e-06, "Neutral": 0.999379, "Positive": 0.000381}}}]}, {"DescriptiveMentionIndex": [0], "Mentions": [{"BeginOffset": 27, "EndOffset": 32, "Score": 0.898127, "GroupScore": 1.0, "Text": "ramen", "Type": "OTHER", "MentionSentiment": {"Sentiment": "NEUTRAL", "SentimentScore": {"Mixed": 0.001046, "Negative": 0.000992, "Neutral": 0.603737, "Positive": 0.394225}}}]}, {"DescriptiveMentionIndex": [0], "Mentions": [{"BeginOffset": 39, "EndOffset": 44, "Score": 0.995008, "GroupScore": 1.0, "Text": "Mango", "Type": "COMMERCIAL_ITEM", "MentionSentiment": {"Sentiment": "NEUTRAL", "SentimentScore": {"Mixed": 0.0, "Negative": 0.0, "Neutral": 0.999966, "Positive": 3.3e-05}}}]}, {"DescriptiveMentionIndex": [0], "Mentions": [{"BeginOffset": 45, "EndOffset": 49, "Score": 0.698375, "GroupScore": 1.0, "Text": "Boba", "Type": "OTHER", "MentionSentiment": {"Sentiment": "POSITIVE", "SentimentScore": {"Mixed": 0.000247, "Negative": 0.000649, "Neutral": 0.33652, "Positive": 0.662584}}}]}, {"DescriptiveMentionIndex": [0], "Mentions": [{"BeginOffset": 54, "EndOffset": 58, "Score": 0.782006, "GroupScore": 1.0, "Text": "both", "Type": "QUANTITY", "MentionSentiment": {"Sentiment": "POSITIVE", "SentimentScore": {"Mixed": 0.0, "Negative": 3e-06, "Neutral": 3e-06, "Positive": 0.999994}}}]}], "File": "review61.txt"}
